sidmkit/__init__.py
sidmkit/averaging.py
sidmkit/bench.py
sidmkit/cli.py
sidmkit/constants.py
sidmkit/constraints.py
sidmkit/cross_sections.py
sidmkit/distributions.py
sidmkit/halo.py
sidmkit/inference.py
sidmkit/model.py
sidmkit/rates.py
sidmkit/scan.py
sidmkit/sparc_batch.py
sidmkit/validate.py
sidmkit/likelihoods/__init__.py
sidmkit/likelihoods/point_constraints.py
sidmkit/likelihoods/rotation_curve.py
sidmkit-0.3.3.dist-info/licenses/LICENSE
sidmkit-0.3.3.dist-info/METADATA
sidmkit-0.3.3.dist-info/WHEEL
sidmkit-0.3.3.dist-info/entry_points.txt
sidmkit-0.3.3.dist-info/top_level.txt
sidmkit-0.3.3.dist-info/RECORD
