Metadata-Version: 2.4
Name: sidmkit
Version: 0.3.3
Summary: A reproducible toolkit for self-interacting dark matter (SIDM) cross sections, constraints, and SPARC rotation-curve analysis
Author: Nalin Dhiman
License: MIT
Project-URL: Homepage, https://github.com/nalin-dhiman/sidmkit.git
Project-URL: Source, https://github.com/nalin-dhiman//sidmkit
Project-URL: Documentation, https://github.com/nalin-dhiman//sidmkit#readme
Project-URL: Issues, https://github.com/nalin-dhiman//sidmkit/issues
Keywords: dark-matter,astrophysics,sidm,rotation-curves,sparc,galaxy-dynamics
Classifier: Development Status :: 4 - Beta
Classifier: Intended Audience :: Science/Research
Classifier: Topic :: Scientific/Engineering :: Astronomy
Classifier: Topic :: Scientific/Engineering :: Physics
Classifier: License :: OSI Approved :: MIT License
Classifier: Programming Language :: Python :: 3
Classifier: Programming Language :: Python :: 3.10
Classifier: Programming Language :: Python :: 3.11
Classifier: Programming Language :: Python :: 3.12
Requires-Python: >=3.10
License-File: LICENSE
Requires-Dist: numpy>=1.22
Requires-Dist: scipy>=1.9
Provides-Extra: plot
Requires-Dist: matplotlib>=3.6; extra == "plot"
Provides-Extra: sparc
Requires-Dist: matplotlib>=3.6; extra == "sparc"
Provides-Extra: dev
Requires-Dist: pytest; extra == "dev"
Requires-Dist: black; extra == "dev"
Requires-Dist: ruff; extra == "dev"
Dynamic: license-file
